genesis_retrieve_task/__init__.py
genesis_retrieve_task/config.py
genesis_retrieve_task/database.py
genesis_retrieve_task/processor.py
genesis_retrieve_task-0.1.1.dist-info/METADATA
genesis_retrieve_task-0.1.1.dist-info/WHEEL
genesis_retrieve_task-0.1.1.dist-info/RECORD
