Metadata-Version: 2.1
Name: genesis-retrieve-task
Version: 0.1.1
Summary: Task retrieval service for Genesis video processing pipeline
Author: stevenge
Author-email: stevenge@godscode.com.cn
Requires-Python: >=3.12,<4.0
Classifier: Programming Language :: Python :: 3
Classifier: Programming Language :: Python :: 3.12
Requires-Dist: cryptography (>=42.0.0,<43.0.0)
Requires-Dist: genesis-base (>=0.1.0,<0.2.0)
Requires-Dist: pymongo (>=4.6.1,<5.0.0)
Requires-Dist: pymysql (>=1.1.0,<2.0.0)
Requires-Dist: python-dotenv (>=1.0.0,<2.0.0)
Requires-Dist: sqlalchemy (>=1.4.0,<2.0.0)
